fake.py
fake_py-0.12.2.dist-info/licenses/LICENSE
fakepy/__init__.py
fake_py-0.12.2.dist-info/METADATA
fake_py-0.12.2.dist-info/WHEEL
fake_py-0.12.2.dist-info/entry_points.txt
fake_py-0.12.2.dist-info/top_level.txt
fake_py-0.12.2.dist-info/RECORD
