Metadata-Version: 2.4
Name: fake.py
Version: 0.12.2
Summary: Minimalistic, standalone alternative fake data generator with no dependencies.
Author-email: Artur Barseghyan <artur.barseghyan@gmail.com>
Maintainer-email: Artur Barseghyan <artur.barseghyan@gmail.com>
License-Expression: MIT
Project-URL: Homepage, https://github.com/barseghyanartur/fake.py/
Project-URL: Issues, https://github.com/barseghyanartur/fake.py/issues
Project-URL: Documentation, https://fakepy.readthedocs.io/
Project-URL: Repository, https://github.com/barseghyanartur/fake.py/
Project-URL: Changelog, https://fakepy.readthedocs.io/en/latest/changelog.html
Keywords: fake data,test data
Classifier: Development Status :: 4 - Beta
Classifier: Intended Audience :: Developers
Classifier: Operating System :: OS Independent
Classifier: Programming Language :: Python :: 3
Classifier: Programming Language :: Python :: 3.10
Classifier: Programming Language :: Python :: 3.11
Classifier: Programming Language :: Python :: 3.12
Classifier: Programming Language :: Python :: 3.13
Classifier: Programming Language :: Python :: 3.14
Classifier: Programming Language :: Python :: 3.15
Classifier: Programming Language :: Python :: 3.9
Classifier: Programming Language :: Python
Classifier: Topic :: Software Development :: Testing
Classifier: Topic :: Software Development
License-File: LICENSE
Provides-Extra: all
Requires-Dist: fake.py[dev,docs,test]; extra == "all"
Provides-Extra: dev
Requires-Dist: build; extra == "dev"
Requires-Dist: detect-secrets; extra == "dev"
Requires-Dist: doc8; extra == "dev"
Requires-Dist: ipython; extra == "dev"
Requires-Dist: mypy; extra == "dev"
Requires-Dist: pkginfo; extra == "dev"
Requires-Dist: pydoclint; extra == "dev"
Requires-Dist: ruff; extra == "dev"
Requires-Dist: twine; extra == "dev"
Requires-Dist: uv; extra == "dev"
Requires-Dist: wheel; extra == "dev"
Provides-Extra: test
Requires-Dist: django; extra == "test"
Requires-Dist: pytest; extra == "test"
Requires-Dist: pytest-cov; extra == "test"
Requires-Dist: pytest-django; extra == "test"
Requires-Dist: pytest-codeblock; extra == "test"
Provides-Extra: docs
Requires-Dist: sphinx; extra == "docs"
Requires-Dist: sphinx-autobuild; extra == "docs"
Requires-Dist: sphinx-rtd-theme>=1.3.0; extra == "docs"
Requires-Dist: sphinx-no-pragma; extra == "docs"
Requires-Dist: sphinx-markdown-builder; extra == "docs"
Requires-Dist: sphinx-llms-txt-link; extra == "docs"
Dynamic: license-file
